gpsexif/__init__.py
gpsexif/reader.py
gpsexif/writer.py
gpsexif-0.3.dist-info/LICENSE
gpsexif-0.3.dist-info/METADATA
gpsexif-0.3.dist-info/WHEEL
gpsexif-0.3.dist-info/top_level.txt
gpsexif-0.3.dist-info/RECORD
