Metadata-Version: 2.1
Name: gpsexif
Version: 0.3
Summary: Writing / Reading GPS coordinates in photo's EXIF by Python.
Home-page: https://github.com/geoyee/GPS-EXIF
Author: geoyee
Author-email: geoyee@yeah.net
License: UNKNOWN
Platform: UNKNOWN
Classifier: Programming Language :: Python :: 3
Classifier: License :: OSI Approved :: MIT License
Classifier: Operating System :: OS Independent
License-File: LICENSE
Requires-Dist: piexif
Requires-Dist: typing
Requires-Dist: numpy
